{
  "main": {
    "id": "3fb2f1f92276162a",
    "type": "split",
    "children": [
      {
        "id": "e1df16a1fcfb0bf2",
        "type": "tabs",
        "children": [
          {
            "id": "43473fec58789c46",
            "type": "leaf",
            "state": {
              "type": "empty",
              "state": {}
            }
          }
        ]
      }
    ],
    "direction": "vertical"
  },
  "left": {
    "id": "86e0051ca37d3909",
    "type": "split",
    "children": [
      {
        "id": "2a245c4329ad41c0",
        "type": "tabs",
        "children": [
          {
            "id": "ef34c23521ef6b44",
            "type": "leaf",
            "state": {
              "type": "file-explorer",
              "state": {
                "sortOrder": "alphabeticalReverse"
              }
            }
          },
          {
            "id": "5d270b2d6642a581",
            "type": "leaf",
            "state": {
              "type": "starred",
              "state": {}
            }
          },
          {
            "id": "5f6b1da240bb885c",
            "type": "leaf",
            "state": {
              "type": "recent-files",
              "state": {}
            }
          },
          {
            "id": "df80e3bdf75af13b",
            "type": "leaf",
            "state": {
              "type": "search",
              "state": {
                "query": "Sói",
                "matchingCase": false,
                "explainSearch": true,
                "collapseAll": false,
                "extraContext": false,
                "sortOrder": "alphabetical"
              }
            }
          }
        ]
      }
    ],
    "direction": "horizontal",
    "width": 267.5110321044922
  },
  "right": {
    "id": "98ee6c8f963969f5",
    "type": "split",
    "children": [
      {
        "id": "0d65db211cf53773",
        "type": "tabs",
        "children": [
          {
            "id": "a1ed3599412e6ece",
            "type": "leaf",
            "state": {
              "type": "localgraph",
              "state": {
                "options": {
                  "collapse-filter": true,
                  "search": "",
                  "localJumps": 1,
                  "localBacklinks": true,
                  "localForelinks": true,
                  "localInterlinks": false,
                  "showTags": false,
                  "showAttachments": false,
                  "hideUnresolved": false,
                  "collapse-color-groups": true,
                  "colorGroups": [],
                  "collapse-display": true,
                  "showArrow": false,
                  "textFadeMultiplier": 0,
                  "nodeSizeMultiplier": 1,
                  "lineSizeMultiplier": 1,
                  "collapse-forces": true,
                  "centerStrength": 0.518713248970312,
                  "repelStrength": 10,
                  "linkStrength": 1,
                  "linkDistance": 250,
                  "scale": 0.7132754626224446,
                  "close": true
                }
              }
            }
          },
          {
            "id": "a6509e8a3f82d1e7",
            "type": "leaf",
            "state": {
              "type": "outline",
              "state": {}
            }
          },
          {
            "id": "91b839172ae5964f",
            "type": "leaf",
            "state": {
              "type": "tag",
              "state": {
                "sortOrder": "frequency",
                "useHierarchy": true
              }
            }
          },
          {
            "id": "835d0a44466bbce2",
            "type": "leaf",
            "state": {
              "type": "advanced-tables-toolbar",
              "state": {}
            }
          },
          {
            "id": "a67c30cd21094fb6",
            "type": "leaf",
            "state": {
              "type": "outline",
              "state": {}
            }
          },
          {
            "id": "d749ce88fd835e09",
            "type": "leaf",
            "state": {
              "type": "calendar",
              "state": {}
            }
          },
          {
            "id": "ad913a9225abbc09",
            "type": "leaf",
            "state": {
              "type": "FANTASY_CALENDAR",
              "state": {}
            }
          },
          {
            "id": "c1c74ad4a417422b",
            "type": "leaf",
            "state": {
              "type": "git-view",
              "state": {}
            }
          },
          {
            "id": "f22e8a044d07a790",
            "type": "leaf",
            "state": {
              "type": "backlink",
              "state": {
                "collapseAll": false,
                "extraContext": false,
                "sortOrder": "alphabetical",
                "showSearch": false,
                "searchQuery": "",
                "backlinkCollapsed": false,
                "unlinkedCollapsed": true
              }
            }
          }
        ],
        "currentTab": 1
      }
    ],
    "direction": "horizontal",
    "width": 450.5
  },
  "left-ribbon": {
    "hiddenItems": {
      "table-editor-obsidian:Advanced Tables Toolbar": false,
      "obsidian-excalidraw-plugin:New Excalidraw drawing": false,
      "obsidian-leaflet-plugin:Open Leaflet Map": false,
      "templater-obsidian:Templater": false,
      "obsidian-map-view:Open map view": false,
      "fantasy-calendar:Open Large Fantasy Calendar": false,
      "switcher:Open quick switcher": false,
      "canvas:Create new canvas": false,
      "daily-notes:Open today's daily note": false,
      "command-palette:Open command palette": false,
      "random-note:Open random note": false,
      "graph:Open graph view": false,
      "breadcrumbs:Breadcrumbs Visualisation": false
    }
  },
  "active": "43473fec58789c46",
  "lastOpenFiles": [
    "Reference_Box/Articles/@ ybox.vn, Hiểu Về Vô Thức Tập Thể (The Collective Unconscious) Theo Quan Điểm Của Nhà Tâm Lý Học Carl Jung.md",
    "Reference_Box/Articles/leananki.com, Zettelkasten Method How to Take Smart Notes for Knowledge Management.md",
    "Reference_Box/Articles/@ ichi.pro, Chủ nghĩa hiện sinh vs Chủ nghĩa hư vô.md",
    "Reference_Box/Articles/benhnhietdoi.vn, Đại cương về Coronavirus.md",
    "Reference_Box/Articles/@ The Architecture of Open Source Applications (Volume 2) GDB.md",
    "Reference_Box/Articles/@ yinote_ Cơ bản về TÔNG PHÁI PHẬT GIÁO và câu hỏi Chiếm dụng Danh tính _ Triết học Đại chúng _ Hội Đồng Cừu - YouTube.md",
    "Zet/Concept/Phật giáo Đại thừa.md",
    "Zet/Concept/Phật giáo Tiểu thừa.md",
    "Zet/Concept/Tịnh độ tông.md",
    "Zet/Phật giáo Nam Tông.md"
  ]
}